{"cameraMode":{"drawMode":0,"name":"Shaded","section":"Shading Mode"},"sceneLighting":true,"audioPlay":false,"sceneViewState":{"m_AlwaysRefresh":false,"showFog":true,"showSkybox":true,"showFlares":true,"showImageEffects":true,"showParticleSystems":true,"showVisualEffectGraphs":true,"m_FxEnabled":true},"in2DMode":false,"pivot":{"x":1.3222274780273438,"y":1.618973731994629,"z":-2.107786178588867},"rotation":{"x":-0.059339363127946857,"y":0.9306103587150574,"z":-0.17469345033168794,"w":-0.31610724329948428},"size":10.0,"orthographic":false}